lumipallo/__init__.py
lumipallo/lumipallo.py
lumipallo/testdata/01_deu_eng_pairs.txt
lumipallo/testdata/01_deu_sentences.txt
lumipallo/testdata/01_eng_sentences.txt
lumipallo-0.0.2.dist-info/LICENSE
lumipallo-0.0.2.dist-info/METADATA
lumipallo-0.0.2.dist-info/WHEEL
lumipallo-0.0.2.dist-info/entry_points.txt
lumipallo-0.0.2.dist-info/top_level.txt
lumipallo-0.0.2.dist-info/RECORD
